slopsquat_detector/__init__.py
slopsquat_detector/cli.py
slopsquat_detector/scanner.py
slopsquat_detector/similarity.py
slopsquat_detector/validator.py
slopsquat_detector-0.3.dist-info/licenses/LICENSE
slopsquat_detector-0.3.dist-info/METADATA
slopsquat_detector-0.3.dist-info/WHEEL
slopsquat_detector-0.3.dist-info/entry_points.txt
slopsquat_detector-0.3.dist-info/top_level.txt
slopsquat_detector-0.3.dist-info/RECORD
