Metadata-Version: 2.4
Name: slopsquat-detector
Version: 0.3
Summary: A Python package that detects and warns against slopsquatted or suspicious import statements in code, helping developers avoid accidentally using malicious or mistyped packages suggested by LLMs or found in legacy code.
Author-email: Prashant Pandey <prashantpandeyiuet@gmail.com>
Project-URL: Homepage, https://github.com/prashantpandeygit/slopsquat
Project-URL: Documentation, https://github.com/prashantpandeygit/slopsquat#readme
Requires-Python: >=3.8
License-File: LICENSE
Requires-Dist: requests>=2.25.1
Provides-Extra: test
Requires-Dist: pytest; extra == "test"
Requires-Dist: requests-mock; extra == "test"
Dynamic: license-file
